imp/__init__.py
imp/imp.py
fastapi_imp-0.0.1.dist-info/METADATA
fastapi_imp-0.0.1.dist-info/WHEEL
fastapi_imp-0.0.1.dist-info/top_level.txt
fastapi_imp-0.0.1.dist-info/RECORD
